[{"inputs":[{"internalType":"address","name":"root_","type":"address"},{"internalType":"address","name":"currency_","type":"address"},{"internalType":"uint256","name":"tokenAmountForONE_","type":"uint256"},{"internalType":"address","name":"juniorTrancheFab_","type":"address"},{"internalType":"address","name":"assessorFab_","type":"address"},{"internalType":"address","name":"juniorOperatorFab_","type":"address"},{"internalType":"address","name":"distributorFab_","type":"address"},{"internalType":"address","name":"seniorTrancheFab_","type":"address"},{"internalType":"address","name":"seniorOperatorFab_","type":"address"}],"payable":false,"stateMutability":"nonpayable","type":"constructor"},{"constant":true,"inputs":[],"name":"assessor","outputs":[{"internalType":"address","name":"","type":"address"}],"payable":false,"stateMutability":"view","type":"function"},{"constant":true,"inputs":[],"name":"assessorFab","outputs":[{"internalType":"contract AssessorFab","name":"","type":"address"}],"payable":false,"stateMutability":"view","type":"function"},{"constant":true,"inputs":[],"name":"currency","outputs":[{"internalType":"address","name":"","type":"address"}],"payable":false,"stateMutability":"view","type":"function"},{"constant":false,"inputs":[],"name":"deploy","outputs":[],"payable":false,"stateMutability":"nonpayable","type":"function"},{"constant":false,"inputs":[],"name":"deployAssessor","outputs":[],"payable":false,"stateMutability":"nonpayable","type":"function"},{"constant":false,"inputs":[],"name":"deployDistributor","outputs":[],"payable":false,"stateMutability":"nonpayable","type":"function"},{"constant":false,"inputs":[],"name":"deployJuniorOperator","outputs":[],"payable":false,"stateMutability":"nonpayable","type":"function"},{"constant":false,"inputs":[],"name":"deployJuniorTranche","outputs":[],"payable":false,"stateMutability":"nonpayable","type":"function"},{"constant":false,"inputs":[],"name":"deploySeniorOperator","outputs":[],"payable":false,"stateMutability":"nonpayable","type":"function"},{"constant":false,"inputs":[],"name":"deploySeniorTranche","outputs":[],"payable":false,"stateMutability":"nonpayable","type":"function"},{"constant":true,"inputs":[],"name":"distributor","outputs":[{"internalType":"address","name":"","type":"address"}],"payable":false,"stateMutability":"view","type":"function"},{"constant":true,"inputs":[],"name":"distributorFab","outputs":[{"internalType":"contract DistributorFab","name":"","type":"address"}],"payable":false,"stateMutability":"view","type":"function"},{"constant":true,"inputs":[],"name":"junior","outputs":[{"internalType":"address","name":"","type":"address"}],"payable":false,"stateMutability":"view","type":"function"},{"constant":true,"inputs":[],"name":"juniorOperator","outputs":[{"internalType":"address","name":"","type":"address"}],"payable":false,"stateMutability":"view","type":"function"},{"constant":true,"inputs":[],"name":"juniorOperatorFab","outputs":[{"internalType":"contract OperatorFab","name":"","type":"address"}],"payable":false,"stateMutability":"view","type":"function"},{"constant":true,"inputs":[],"name":"juniorTrancheFab","outputs":[{"internalType":"contract TrancheFab","name":"","type":"address"}],"payable":false,"stateMutability":"view","type":"function"},{"constant":true,"inputs":[],"name":"senior","outputs":[{"internalType":"address","name":"","type":"address"}],"payable":false,"stateMutability":"view","type":"function"},{"constant":true,"inputs":[],"name":"seniorOperator","outputs":[{"internalType":"address","name":"","type":"address"}],"payable":false,"stateMutability":"view","type":"function"},{"constant":true,"inputs":[],"name":"seniorOperatorFab","outputs":[{"internalType":"contract OperatorFab","name":"","type":"address"}],"payable":false,"stateMutability":"view","type":"function"},{"constant":true,"inputs":[],"name":"seniorTrancheFab","outputs":[{"internalType":"contract SeniorTrancheFab","name":"","type":"address"}],"payable":false,"stateMutability":"view","type":"function"},{"constant":true,"inputs":[],"name":"tokenAmountForONE","outputs":[{"internalType":"uint256","name":"","type":"uint256"}],"payable":false,"stateMutability":"view","type":"function"}]
